MANIFEST.in
README.md
setup.cfg
setup.py
XC_loc/XC_main.py
XC_loc/XC_plotting.py
XC_loc/__init__.py
XC_loc/default_vel_model.tvel
XC_loc/xcorr_Tools.py
XC_loc/xloc_Tools.py
XC_loc.egg-info/PKG-INFO
XC_loc.egg-info/SOURCES.txt
XC_loc.egg-info/dependency_links.txt
XC_loc.egg-info/requires.txt
XC_loc.egg-info/top_level.txt