Metadata-Version: 1.1
Name: XC-loc
Version: 1.0.6
Summary: XC_loc - envelope cross-correlation location method
Home-page: https://github.com/awech/XC_loc
Author: Aaron Wech
Author-email: awech@usgs.gov
License: LGPL
Download-URL: https://github.com/awech/XC_loc/archive/v1.0.6.tar.gz
Keywords: envelope cross correlation,seimsology,tremor
Platform: UNKNOWN
Classifier: Development Status :: 4 - Beta
Classifier: Intended Audience :: Science/Research
Classifier: Topic :: Scientific/Engineering
Classifier: License :: OSI Approved :: GNU General Public License v3 (GPLv3)
Classifier: Programming Language :: Python :: 3.7
Classifier: Programming Language :: Python :: 3.8
